mcp_vision_stat/__init__.py
mcp_vision_stat/__main__.py
mcp_vision_stat/server.py
mcp_vision_stat-0.2.2.dist-info/METADATA
mcp_vision_stat-0.2.2.dist-info/WHEEL
mcp_vision_stat-0.2.2.dist-info/entry_points.txt
mcp_vision_stat-0.2.2.dist-info/RECORD
